examples/__init__.py
examples/kafka_chained_join.py
examples/kafka_join_multistreams.py
examples/kafka_join_streams.py
examples/kafka_single_stream.py
examples/kafka_ssl.py
examples/manual_result_commit.py
examples/read_kafka_write_file.py
examples/single_input_multiple_results.py
examples/single_stream.py
examples/single_stream_with_result.py
examples/stop_stream_processing.py
examples/time_based_window_fetch.py
examples/window_fetch.py
examples/window_parallel_streams.py
examples/windowed_join_fetch.py
tests/__init__.py
tests/test_expressions.py
tests/test_join_tree.py
watermill/__init__.py
watermill/expressions.py
watermill/mill.py
watermill/stream_join.py
watermill/stream_types.py
watermill/windows.py
watermill/message_brokers/__init__.py
watermill/message_brokers/json_file_message_broker.py
watermill/message_brokers/kafka_message_broker.py
watermill/message_brokers/message_broker.py
watermill-3.6.7.dist-info/LICENSE
watermill-3.6.7.dist-info/METADATA
watermill-3.6.7.dist-info/WHEEL
watermill-3.6.7.dist-info/top_level.txt
watermill-3.6.7.dist-info/RECORD
