Metadata-Version: 2.1
Name: watermill
Version: 3.6.7
Summary: Watermill data stream organizing framework.
Home-page: https://gitlab.com/kraevs/watermill
Author: Stanislav Kraev
Author-email: stanislav.kraev@gmail.com
License: MIT
Project-URL: Code, https://gitlab.com/kraevs/watermill
Project-URL: Issue tracker, https://gitlab.com/kraevs/watermill/issues
Platform: any
Classifier: License :: OSI Approved :: MIT License
Classifier: Programming Language :: Python :: 3.6
Classifier: Programming Language :: Python :: 3.7
Classifier: Programming Language :: Python :: 3.8
Requires-Python: >=3.6
Requires-Dist: botox-di (==1.5.0)
Requires-Dist: dataclass-factory (==2.8.1)
Requires-Dist: dataclasses ; python_version < "3.7"
